LICENCE.txt
MANIFEST.in
README.rst
pyproject.toml
setup.cfg
setup.py
django_blog_lotus.egg-info/PKG-INFO
django_blog_lotus.egg-info/SOURCES.txt
django_blog_lotus.egg-info/dependency_links.txt
django_blog_lotus.egg-info/requires.txt
django_blog_lotus.egg-info/top_level.txt
django_blog_lotus.egg-info/zip-safe
lotus/__init__.py
lotus/admin_filters.py
lotus/api_urls.py
lotus/apps.py
lotus/choices.py
lotus/exceptions.py
lotus/formfields.py
lotus/lookups.py
lotus/managers.py
lotus/responses.py
lotus/settings.py
lotus/urls.py
lotus/admin/__init__.py
lotus/admin/album.py
lotus/admin/article.py
lotus/admin/category.py
lotus/compat/__init__.py
lotus/compat/default_storage.py
lotus/compat/import_zoneinfo.py
lotus/contrib/__init__.py
lotus/contrib/disk.py
lotus/contrib/django_configuration.py
lotus/factories/__init__.py
lotus/factories/album.py
lotus/factories/article.py
lotus/factories/author.py
lotus/factories/category.py
lotus/factories/tag.py
lotus/forms/__init__.py
lotus/forms/album.py
lotus/forms/article.py
lotus/forms/category.py
lotus/forms/translated.py
lotus/locale/django.pot
lotus/locale/de/LC_MESSAGES/django.mo
lotus/locale/de/LC_MESSAGES/django.po
lotus/locale/en/LC_MESSAGES/django.mo
lotus/locale/en/LC_MESSAGES/django.po
lotus/locale/fr/LC_MESSAGES/django.mo
lotus/locale/fr/LC_MESSAGES/django.po
lotus/management/__init__.py
lotus/management/commands/__init__.py
lotus/management/commands/lotus_demo.py
lotus/migrations/0001_initial.py
lotus/migrations/0002_add_album.py
lotus/migrations/0003_album_modified_category_modified_and_more.py
lotus/migrations/0004_add_category_tree.py
lotus/migrations/0005_add_article_category_alt_text.py
lotus/migrations/0006_add_article_category_template.py
lotus/migrations/__init__.py
lotus/models/__init__.py
lotus/models/album.py
lotus/models/article.py
lotus/models/author.py
lotus/models/category.py
lotus/models/translated.py
lotus/serializers/__init__.py
lotus/serializers/album.py
lotus/serializers/article.py
lotus/serializers/author.py
lotus/serializers/category.py
lotus/sitemaps/__init__.py
lotus/sitemaps/article.py
lotus/sitemaps/author.py
lotus/sitemaps/category.py
lotus/sitemaps/tag.py
lotus/sitemaps/translated.py
lotus/static/css/lotus-admin.css
