Metadata-Version: 2.4
Name: django-blog-lotus
Version: 0.9.4
Summary: A weblog application with Django.
Home-page: https://github.com/emencia/django-blog-lotus
Author: Emencia
Author-email: support@emencia.com
License: MIT
Project-URL: Source Code, https://github.com/emencia/django-blog-lotus
Project-URL: Issue Tracker, https://github.com/emencia/django-blog-lotus/issues
Project-URL: Changelog, https://django-blog-lotus.readthedocs.io/en/latest/history.html
Project-URL: Documentation, https://django-blog-lotus.readthedocs.io/
Keywords: Python Django Blog
Classifier: Development Status :: 5 - Production/Stable
Classifier: Operating System :: OS Independent
Classifier: Intended Audience :: Developers
Classifier: License :: OSI Approved :: MIT License
Classifier: Natural Language :: English
Classifier: Programming Language :: Python :: 3
Classifier: Programming Language :: Python :: 3.9
Classifier: Programming Language :: Python :: 3.10
Classifier: Programming Language :: Python :: 3.11
Classifier: Framework :: Django
Classifier: Framework :: Django :: 3.2
Classifier: Framework :: Django :: 4.0
Classifier: Framework :: Django :: 4.1
Classifier: Framework :: Django :: 4.2
Classifier: Framework :: Django :: 5.0
Classifier: Framework :: Django :: 5.1
Classifier: Framework :: Django :: 5.2
Classifier: Intended Audience :: Developers
Classifier: Topic :: Internet :: WWW/HTTP
Classifier: Topic :: Software Development :: Libraries :: Python Modules
Requires-Python: >=3.9
License-File: LICENCE.txt
Requires-Dist: django>=3.2
Requires-Dist: django-ckeditor>=6.0.0
Requires-Dist: django-taggit>=3.1.0
Requires-Dist: django-autocomplete-light>=3.9.7
Requires-Dist: django-smart-media>=0.2.2
Requires-Dist: django-treebeard!=4.5,>=4.3
Provides-Extra: api
Requires-Dist: djangorestframework>=3.14.0; extra == "api"
Provides-Extra: breadcrumbs
Requires-Dist: django-view-breadcrumbs>=2.2.4; extra == "breadcrumbs"
Provides-Extra: dev
Requires-Dist: pillow>=8.0.0; extra == "dev"
Requires-Dist: pytest>=7.0; extra == "dev"
Requires-Dist: pytest-django>=4.5.2; extra == "dev"
Requires-Dist: factory-boy>=3.3.0; extra == "dev"
Requires-Dist: pyquery>=2.0.0; extra == "dev"
Requires-Dist: freezegun>=1.2.0; extra == "dev"
Requires-Dist: diskette>=0.3.6; extra == "dev"
Provides-Extra: quality
Requires-Dist: flake8>=6.0.0; extra == "quality"
Requires-Dist: tox>=4.11.0; extra == "quality"
Provides-Extra: doc
Requires-Dist: sphinx>=8.0.2; extra == "doc"
Requires-Dist: furo>=2024.8.6; extra == "doc"
Requires-Dist: sphinx-copybutton>=0.5.2; extra == "doc"
Provides-Extra: doc-live
Requires-Dist: livereload>=2.6.0; extra == "doc-live"
Provides-Extra: release
Requires-Dist: twine>=5.0.0; extra == "release"
Provides-Extra: sandbox
Requires-Dist: drf-redesign>=0.4.0; extra == "sandbox"
Dynamic: license-file
